{
  "env": "MountainCar-v0",
  "gens": 25,
  "n_seeds": 3,
  "pop_size": 40,
  "tag": "r13_mountaincar",
  "algos": {
    "neat": {
      "runs": [
        {
          "seed": 0,
          "history": [
            {
              "gen": 1,
              "best": 0.0,
              "mean": -70.0,
              "num_species": 1,
              "avg_complexity": 6.0,
              "max_complexity": 6
            },
            {
              "gen": 2,
              "best": 0.0,
              "mean": -45.0,
              "num_species": 1,
              "avg_complexity": 6.0,
              "max_complexity": 6
            },
            {
              "gen": 3,
              "best": 0.0,
              "mean": -75.0,
              "num_species": 1,
              "avg_complexity": 6.05,
              "max_complexity": 8
            },
            {
              "gen": 4,
              "best": 0.0,
              "mean": -45.0,
              "num_species": 1,
              "avg_complexity": 6.1,
              "max_complexity": 8
            },
            {
              "gen": 5,
              "best": 0.0,
              "mean": -60.0,
              "num_species": 1,
              "avg_complexity": 6.725,
              "max_complexity": 10
            },
            {
              "gen": 6,
              "best": 0.0,
              "mean": -120.0,
              "num_species": 2,
              "avg_complexity": 9.3,
              "max_complexity": 12
            },
            {
              "gen": 7,
              "best": 0.0,
              "mean": -135.0,
              "num_species": 5,
              "avg_complexity": 9.875,
              "max_complexity": 12
            },
            {
              "gen": 8,
              "best": -200.0,
              "mean": -200.0,
              "num_species": 6,
              "avg_complexity": 9.375,
              "max_complexity": 11
            },
            {
              "gen": 9,
              "best": -200.0,
              "mean": -200.0,
              "num_species": 6,
              "avg_complexity": 9.4,
              "max_complexity": 13
            },
            {
              "gen": 10,
              "best": -200.0,
              "mean": -200.0,
              "num_species": 7,
              "avg_complexity": 9.85,
              "max_complexity": 13
            },
            {
              "gen": 11,
              "best": -200.0,
              "mean": -200.0,
              "num_species": 7,
              "avg_complexity": 9.9,
              "max_complexity": 13
            },
            {
              "gen": 12,
              "best": -191.33333333333334,
              "mean": -198.7,
              "num_species": 7,
              "avg_complexity": 9.975,
              "max_complexity": 13
            },
            {
              "gen": 13,
              "best": -184.0,
              "mean": -197.6,
              "num_species": 7,
              "avg_complexity": 9.925,
              "max_complexity": 14
            },
            {
              "gen": 14,
              "best": -178.66666666666666,
              "mean": -196.8,
              "num_species": 7,
              "avg_complexity": 9.925,
              "max_complexity": 13
            },
            {
              "gen": 15,
              "best": -175.33333333333334,
              "mean": -196.3,
              "num_species": 7,
              "avg_complexity": 9.925,
              "max_complexity": 13
            },
            {
              "gen": 16,
              "best": -162.66666666666666,
              "mean": -194.4,
              "num_species": 7,
              "avg_complexity": 9.95,
              "max_complexity": 13
            },
            {
              "gen": 17,
              "best": -118.33333333333333,
              "mean": -187.75,
              "num_species": 7,
              "avg_complexity": 9.875,
              "max_complexity": 13
            },
            {
              "gen": 18,
              "best": -162.0,
              "mean": -194.3,
              "num_species": 7,
              "avg_complexity": 10.05,
              "max_complexity": 13
            },
            {
              "gen": 19,
              "best": -165.66666666666666,
              "mean": -194.85,
              "num_species": 7,
              "avg_complexity": 9.975,
              "max_complexity": 15
            },
            {
              "gen": 20,
              "best": -163.0,
              "mean": -194.45,
              "num_species": 7,
              "avg_complexity": 9.85,
              "max_complexity": 13
            },
            {
              "gen": 21,
              "best": -118.0,
              "mean": -187.7,
              "num_species": 7,
              "avg_complexity": 9.85,
              "max_complexity": 13
            },
            {
              "gen": 22,
              "best": -142.33333333333334,
              "mean": -191.35,
              "num_species": 7,
              "avg_complexity": 9.85,
              "max_complexity": 13
            },
            {
              "gen": 23,
              "best": -164.0,
              "mean": -194.6,
              "num_species": 7,
              "avg_complexity": 9.875,
              "max_complexity": 13
            },
            {
              "gen": 24,
              "best": -162.66666666666666,
              "mean": -194.4,
              "num_species": 7,
              "avg_complexity": 9.875,
              "max_complexity": 13
            },
            {
              "gen": 25,
              "best": -147.0,
              "mean": -192.05,
              "num_species": 7,
              "avg_complexity": 9.85,
              "max_complexity": 13
            }
          ],
          "elapsed_s": 16.5277898311615,
          "final_best_fitness": -176.2,
          "final_best_std": 36.35601738364641,
          "final_best_min": -200.0,
          "final_best_max": -120.0,
          "final_best_evals": [
            -200.0,
            -200.0,
            -200.0,
            -200.0,
            -200.0,
            -121.0,
            -120.0,
            -200.0,
            -200.0,
            -200.0,
            -121.0,
            -200.0,
            -120.0,
            -200.0,
            -121.0,
            -200.0,
            -121.0,
            -200.0,
            -200.0,
            -200.0
          ],
          "final_best_complexity": 13,
          "final_best_hidden": 3,
          "first_solve_gen": 1,
          "best_ever_training_score": -1000000000.0
        },
        {
          "seed": 1,
          "history": [
            {
              "gen": 1,
              "best": 0.0,
              "mean": -37.35,
              "num_species": 1,
              "avg_complexity": 6.05,
              "max_complexity": 8
            },
            {
              "gen": 2,
              "best": 0.0,
              "mean": -54.025,
              "num_species": 1,
              "avg_complexity": 6.0,
              "max_complexity": 6
            },
            {
              "gen": 3,
              "best": 0.0,
              "mean": -45.275,
              "num_species": 1,
              "avg_complexity": 6.15,
              "max_complexity": 8
            },
            {
              "gen": 4,
              "best": 0.0,
              "mean": -22.75,
              "num_species": 1,
              "avg_complexity": 6.725,
              "max_complexity": 10
            },
            {
              "gen": 5,
              "best": 0.0,
              "mean": -135.98333333333335,
              "num_species": 3,
              "avg_complexity": 8.375,
              "max_complexity": 12
            },
            {
              "gen": 6,
              "best": 0.0,
              "mean": -65.96666666666667,
              "num_species": 3,
              "avg_complexity": 8.375,
              "max_complexity": 11
            },
            {
              "gen": 7,
              "best": 0.0,
              "mean": -38.916666666666664,
              "num_species": 3,
              "avg_complexity": 8.35,
              "max_complexity": 11
            },
            {
              "gen": 8,
              "best": 0.0,
              "mean": -66.03333333333333,
              "num_species": 3,
              "avg_complexity": 8.55,
              "max_complexity": 13
            },
            {
              "gen": 9,
              "best": 0.0,
              "mean": -94.25,
              "num_species": 4,
              "avg_complexity": 9.575,
              "max_complexity": 14
            },
            {
              "gen": 10,
              "best": 0.0,
              "mean": -59.725,
              "num_species": 4,
              "avg_complexity": 9.6,
              "max_complexity": 14
            },
            {
              "gen": 11,
              "best": 0.0,
              "mean": -55.55,
              "num_species": 4,
              "avg_complexity": 10.15,
              "max_complexity": 15
            },
            {
              "gen": 12,
              "best": 0.0,
              "mean": -64.425,
              "num_species": 4,
              "avg_complexity": 9.9,
              "max_complexity": 13
            },
            {
              "gen": 13,
              "best": 0.0,
              "mean": -55.525,
              "num_species": 4,
              "avg_complexity": 9.625,
              "max_complexity": 15
            },
            {
              "gen": 14,
              "best": 0.0,
              "mean": -53.275,
              "num_species": 4,
              "avg_complexity": 9.55,
              "max_complexity": 13
            },
            {
              "gen": 15,
              "best": 0.0,
              "mean": -48.85,
              "num_species": 4,
              "avg_complexity": 9.575,
              "max_complexity": 13
            },
            {
              "gen": 16,
              "best": 0.0,
              "mean": -51.39166666666667,
              "num_species": 4,
              "avg_complexity": 9.5,
              "max_complexity": 13
            },
            {
              "gen": 17,
              "best": 0.0,
              "mean": -44.09166666666666,
              "num_species": 4,
              "avg_complexity": 9.6,
              "max_complexity": 14
            },
            {
              "gen": 18,
              "best": 0.0,
              "mean": -59.658333333333324,
              "num_species": 4,
              "avg_complexity": 9.525,
              "max_complexity": 13
            },
            {
              "gen": 19,
              "best": 0.0,
              "mean": -58.9,
              "num_species": 4,
              "avg_complexity": 9.5,
              "max_complexity": 13
            },
            {
              "gen": 20,
              "best": 0.0,
              "mean": -28.3,
              "num_species": 4,
              "avg_complexity": 9.525,
              "max_complexity": 13
            },
            {
              "gen": 21,
              "best": 0.0,
              "mean": -53.13333333333334,
              "num_species": 4,
              "avg_complexity": 9.6,
              "max_complexity": 13
            },
            {
              "gen": 22,
              "best": 0.0,
              "mean": -42.15,
              "num_species": 4,
              "avg_complexity": 9.6,
              "max_complexity": 14
            },
            {
              "gen": 23,
              "best": 0.0,
              "mean": -53.1,
              "num_species": 4,
              "avg_complexity": 9.525,
              "max_complexity": 13
            },
            {
              "gen": 24,
              "best": 0.0,
              "mean": -54.858333333333334,
              "num_species": 4,
              "avg_complexity": 9.55,
              "max_complexity": 15
            },
            {
              "gen": 25,
              "best": 0.0,
              "mean": -58.733333333333334,
              "num_species": 4,
              "avg_complexity": 9.6,
              "max_complexity": 13
            }
          ],
          "elapsed_s": 11.950089931488037,
          "final_best_fitness": -128.45,
          "final_best_std": 24.084175302467802,
          "final_best_min": -200.0,
          "final_best_max": -115.0,
          "final_best_evals": [
            -122.0,
            -127.0,
            -123.0,
            -125.0,
            -200.0,
            -117.0,
            -116.0,
            -200.0,
            -122.0,
            -122.0,
            -116.0,
            -122.0,
            -115.0,
            -121.0,
            -116.0,
            -121.0,
            -116.0,
            -122.0,
            -121.0,
            -125.0
          ],
          "final_best_complexity": 6,
          "final_best_hidden": 0,
          "first_solve_gen": 1,
          "best_ever_training_score": -1000000000.0
        },
        {
          "seed": 2,
          "history": [
            {
              "gen": 1,
              "best": 0.0,
              "mean": -50.0,
              "num_species": 1,
              "avg_complexity": 6.1,
              "max_complexity": 8
            },
            {
              "gen": 2,
              "best": 0.0,
              "mean": -70.0,
              "num_species": 1,
              "avg_complexity": 6.1,
              "max_complexity": 8
            },
            {
              "gen": 3,
              "best": 0.0,
              "mean": -55.0,
              "num_species": 1,
              "avg_complexity": 6.0,
              "max_complexity": 6
            },
            {
              "gen": 4,
              "best": 0.0,
              "mean": -70.0,
              "num_species": 1,
              "avg_complexity": 6.15,
              "max_complexity": 8
            },
            {
              "gen": 5,
              "best": 0.0,
              "mean": -53.2,
              "num_species": 1,
              "avg_complexity": 6.0,
              "max_complexity": 6
            },
            {
              "gen": 6,
              "best": 0.0,
              "mean": -61.533333333333324,
              "num_species": 1,
              "avg_complexity": 6.0,
              "max_complexity": 6
            },
            {
              "gen": 7,
              "best": 0.0,
              "mean": -55.975,
              "num_species": 1,
              "avg_complexity": 6.2,
              "max_complexity": 8
            },
            {
              "gen": 8,
              "best": 0.0,
              "mean": -48.28333333333334,
              "num_species": 1,
              "avg_complexity": 6.85,
              "max_complexity": 9
            },
            {
              "gen": 9,
              "best": 0.0,
              "mean": -138.09166666666667,
              "num_species": 3,
              "avg_complexity": 8.775,
              "max_complexity": 11
            },
            {
              "gen": 10,
              "best": 0.0,
              "mean": -143.01666666666668,
              "num_species": 5,
              "avg_complexity": 10.4,
              "max_complexity": 13
            },
            {
              "gen": 11,
              "best": -126.0,
              "mean": -183.2,
              "num_species": 7,
              "avg_complexity": 10.0,
              "max_complexity": 12
            },
            {
              "gen": 12,
              "best": -147.0,
              "mean": -186.75,
              "num_species": 7,
              "avg_complexity": 10.05,
              "max_complexity": 13
            },
            {
              "gen": 13,
              "best": -123.0,
              "mean": -182.45,
              "num_species": 7,
              "avg_complexity": 10.125,
              "max_complexity": 13
            },
            {
              "gen": 14,
              "best": -124.66666666666667,
              "mean": -177.5,
              "num_species": 7,
              "avg_complexity": 9.95,
              "max_complexity": 11
            },
            {
              "gen": 15,
              "best": -122.0,
              "mean": -176.7,
              "num_species": 7,
              "avg_complexity": 10.025,
              "max_complexity": 12
            },
            {
              "gen": 16,
              "best": -117.66666666666667,
              "mean": -175.4,
              "num_species": 7,
              "avg_complexity": 10.05,
              "max_complexity": 12
            },
            {
              "gen": 17,
              "best": -145.66666666666666,
              "mean": -183.8,
              "num_species": 7,
              "avg_complexity": 10.1,
              "max_complexity": 14
            },
            {
              "gen": 18,
              "best": -119.0,
              "mean": -179.83333333333334,
              "num_species": 8,
              "avg_complexity": 10.65,
              "max_complexity": 14
            },
            {
              "gen": 19,
              "best": -120.33333333333333,
              "mean": -180.125,
              "num_species": 8,
              "avg_complexity": 10.55,
              "max_complexity": 14
            },
            {
              "gen": 20,
              "best": -120.33333333333333,
              "mean": -180.125,
              "num_species": 8,
              "avg_complexity": 10.675,
              "max_complexity": 15
            },
            {
              "gen": 21,
              "best": -146.0,
              "mean": -186.54166666666669,
              "num_species": 8,
              "avg_complexity": 10.525,
              "max_complexity": 15
            },
            {
              "gen": 22,
              "best": -128.33333333333334,
              "mean": -185.5,
              "num_species": 8,
              "avg_complexity": 10.525,
              "max_complexity": 14
            },
            {
              "gen": 23,
              "best": -124.0,
              "mean": -183.70833333333331,
              "num_species": 8,
              "avg_complexity": 10.5,
              "max_complexity": 14
            },
            {
              "gen": 24,
              "best": -121.0,
              "mean": -183.45833333333331,
              "num_species": 8,
              "avg_complexity": 10.6,
              "max_complexity": 15
            },
            {
              "gen": 25,
              "best": -119.0,
              "mean": -179.79166666666666,
              "num_species": 8,
              "avg_complexity": 10.575,
              "max_complexity": 16
            }
          ],
          "elapsed_s": 11.99102258682251,
          "final_best_fitness": -121.8,
          "final_best_std": 4.342810150121693,
          "final_best_min": -129.0,
          "final_best_max": -115.0,
          "final_best_evals": [
            -123.0,
            -125.0,
            -124.0,
            -124.0,
            -129.0,
            -117.0,
            -116.0,
            -127.0,
            -124.0,
            -124.0,
            -115.0,
            -123.0,
            -115.0,
            -124.0,
            -115.0,
            -124.0,
            -115.0,
            -124.0,
            -124.0,
            -124.0
          ],
          "final_best_complexity": 10,
          "final_best_hidden": 1,
          "first_solve_gen": 1,
          "best_ever_training_score": -1000000000.0
        }
      ],
      "mean_final": -142.15,
      "std_final": 24.22956183398013,
      "mean_time": 13.489634116490683,
      "mean_complexity": 9.666666666666666,
      "solve_rate": 1.0
    },
    "crit": {
      "runs": [
        {
          "seed": 0,
          "history": [
            {
              "gen": 1,
              "best": 0.0,
              "mean": -140.0,
              "num_species": 3,
              "avg_complexity": 6.05,
              "max_complexity": 8,
              "archive_size": 3,
              "avg_mut_rate": 0.5,
              "eff_novelty_coef": 0.05
            },
            {
              "gen": 2,
              "best": 0.0,
              "mean": -165.0,
              "num_species": 3,
              "avg_complexity": 6.0,
              "max_complexity": 6,
              "archive_size": 6,
              "avg_mut_rate": 0.5,
              "eff_novelty_coef": 0.0485
            },
            {
              "gen": 3,
              "best": 0.0,
              "mean": -115.0,
              "num_species": 3,
              "avg_complexity": 6.05,
              "max_complexity": 8,
              "archive_size": 6,
              "avg_mut_rate": 0.5,
              "eff_novelty_coef": 0.047045000000000003
            },
            {
              "gen": 4,
              "best": 0.0,
              "mean": -145.0,
              "num_species": 3,
              "avg_complexity": 6.575,
              "max_complexity": 11,
              "archive_size": 6,
              "avg_mut_rate": 0.5,
              "eff_novelty_coef": 0.04563365
            },
            {
              "gen": 5,
              "best": 0.0,
              "mean": -140.0,
              "num_species": 5,
              "avg_complexity": 6.7,
              "max_complexity": 8,
              "archive_size": 6,
              "avg_mut_rate": 0.5,
              "eff_novelty_coef": 0.0442646405
            },
            {
              "gen": 6,
              "best": 0.0,
              "mean": -150.0,
              "num_species": 5,
              "avg_complexity": 6.5,
              "max_complexity": 10,
              "archive_size": 6,
              "avg_mut_rate": 0.5,
              "eff_novelty_coef": 0.042936701285
            },
            {
              "gen": 7,
              "best": 0.0,
              "mean": -145.0,
              "num_species": 5,
              "avg_complexity": 6.0,
              "max_complexity": 10,
              "archive_size": 6,
              "avg_mut_rate": 0.5,
              "eff_novelty_coef": 0.04164860024644999
            },
            {
              "gen": 8,
              "best": 0.0,
              "mean": -155.0,
              "num_species": 8,
              "avg_complexity": 5.975,
              "max_complexity": 8,
              "archive_size": 6,
              "avg_mut_rate": 0.5,
              "eff_novelty_coef": 0.040399142239056496
            },
            {
              "gen": 9,
              "best": 0.0,
              "mean": -155.0,
              "num_species": 5,
              "avg_complexity": 5.975,
              "max_complexity": 8,
              "archive_size": 6,
              "avg_mut_rate": 0.5,
              "eff_novelty_coef": 0.0391871679718848
            },
            {
              "gen": 10,
              "best": 0.0,
              "mean": -120.0,
              "num_species": 8,
              "avg_complexity": 6.25,
              "max_complexity": 11,
              "archive_size": 6,
              "avg_mut_rate": 0.5,
              "eff_novelty_coef": 0.03801155293272826
            },
            {
              "gen": 11,
              "best": 0.0,
              "mean": -135.0,
              "num_species": 8,
              "avg_complexity": 6.725,
              "max_complexity": 11,
              "archive_size": 6,
              "avg_mut_rate": 0.5,
              "eff_novelty_coef": 0.03687120634474641
            },
            {
              "gen": 12,
              "best": 0.0,
              "mean": -145.0,
              "num_species": 8,
              "avg_complexity": 7.2,
              "max_complexity": 11,
              "archive_size": 6,
              "avg_mut_rate": 0.5,
              "eff_novelty_coef": 0.03576507015440401
            },
            {
              "gen": 13,
              "best": 0.0,
              "mean": -120.0,
              "num_species": 6,
              "avg_complexity": 6.725,
              "max_complexity": 9,
              "archive_size": 6,
              "avg_mut_rate": 0.5,
              "eff_novelty_coef": 0.03469211804977189
            },
            {
              "gen": 14,
              "best": 0.0,
              "mean": -140.0,
              "num_species": 4,
              "avg_complexity": 6.5,
              "max_complexity": 10,
              "archive_size": 6,
              "avg_mut_rate": 0.5,
              "eff_novelty_coef": 0.03365135450827873
            },
            {
              "gen": 15,
              "best": 0.0,
              "mean": -150.0,
              "num_species": 8,
              "avg_complexity": 6.7,
              "max_complexity": 8,
              "archive_size": 6,
              "avg_mut_rate": 0.5,
              "eff_novelty_coef": 0.03264181387303037
            },
            {
              "gen": 16,
              "best": 0.0,
              "mean": -120.0,
              "num_species": 5,
              "avg_complexity": 6.65,
              "max_complexity": 10,
              "archive_size": 6,
              "avg_mut_rate": 0.5,
              "eff_novelty_coef": 0.031662559456839455
            },
            {
              "gen": 17,
              "best": 0.0,
              "mean": -135.0,
              "num_species": 5,
              "avg_complexity": 5.25,
              "max_complexity": 8,
              "archive_size": 6,
              "avg_mut_rate": 0.5,
              "eff_novelty_coef": 0.030712682673134276
            },
            {
              "gen": 18,
              "best": 0.0,
              "mean": -130.0,
              "num_species": 4,
              "avg_complexity": 5.0,
              "max_complexity": 5,
              "archive_size": 6,
              "avg_mut_rate": 0.5,
              "eff_novelty_coef": 0.029791302192940246
            },
            {
              "gen": 19,
              "best": 0.0,
              "mean": -144.85,
              "num_species": 6,
              "avg_complexity": 5.1,
              "max_complexity": 7,
              "archive_size": 6,
              "avg_mut_rate": 0.5,
              "eff_novelty_coef": 0.02889756312715204
            },
            {
              "gen": 20,
              "best": 0.0,
              "mean": -140.0,
              "num_species": 8,
              "avg_complexity": 5.05,
              "max_complexity": 7,
              "archive_size": 7,
              "avg_mut_rate": 0.5,
              "eff_novelty_coef": 0.028030636233337475
            },
            {
              "gen": 21,
              "best": 0.0,
              "mean": -140.0,
              "num_species": 10,
              "avg_complexity": 5.1,
              "max_complexity": 7,
              "archive_size": 7,
              "avg_mut_rate": 0.5,
              "eff_novelty_coef": 0.02718971714633735
            },
            {
              "gen": 22,
              "best": 0.0,
              "mean": -140.0,
              "num_species": 6,
              "avg_complexity": 5.225,
              "max_complexity": 8,
              "archive_size": 7,
              "avg_mut_rate": 0.5,
              "eff_novelty_coef": 0.02637402563194723
            },
            {
              "gen": 23,
              "best": 0.0,
              "mean": -135.0,
              "num_species": 6,
              "avg_complexity": 5.05,
              "max_complexity": 7,
              "archive_size": 7,
              "avg_mut_rate": 0.5,
              "eff_novelty_coef": 0.025582804862988813
            },
            {
              "gen": 24,
              "best": 0.0,
              "mean": -153.65,
              "num_species": 11,
              "avg_complexity": 5.175,
              "max_complexity": 7,
              "archive_size": 7,
              "avg_mut_rate": 0.5,
              "eff_novelty_coef": 0.024815320717099146
            },
            {
              "gen": 25,
              "best": 0.0,
              "mean": -125.0,
              "num_species": 6,
              "avg_complexity": 5.2,
              "max_complexity": 7,
              "archive_size": 7,
              "avg_mut_rate": 0.5,
              "eff_novelty_coef": 0.02407086109558617
            }
          ],
          "elapsed_s": 12.472826719284058,
          "final_best_fitness": -199.85,
          "final_best_std": 0.3570714214271425,
          "final_best_min": -200.0,
          "final_best_max": -199.0,
          "final_best_evals": [
            -200.0,
            -200.0,
            -200.0,
            -200.0,
            -200.0,
            -200.0,
            -200.0,
            -200.0,
            -200.0,
            -200.0,
            -199.0,
            -200.0,
            -200.0,
            -200.0,
            -199.0,
            -200.0,
            -199.0,
            -200.0,
            -200.0,
            -200.0
          ],
          "final_best_complexity": 5,
          "final_best_hidden": 0,
          "first_solve_gen": 1,
          "best_ever_training_score": -1000000000.0
        },
        {
          "seed": 1,
          "history": [
            {
              "gen": 1,
              "best": 0.0,
              "mean": -157.35,
              "num_species": 5,
              "avg_complexity": 6.0,
              "max_complexity": 6,
              "archive_size": 5,
              "avg_mut_rate": 0.5,
              "eff_novelty_coef": 0.05
            },
            {
              "gen": 2,
              "best": 0.0,
              "mean": -139.625,
              "num_species": 4,
              "avg_complexity": 6.0,
              "max_complexity": 6,
              "archive_size": 5,
              "avg_mut_rate": 0.5,
              "eff_novelty_coef": 0.0485
            },
            {
              "gen": 3,
              "best": 0.0,
              "mean": -150.5,
              "num_species": 4,
              "avg_complexity": 6.0,
              "max_complexity": 6,
              "archive_size": 5,
              "avg_mut_rate": 0.5,
              "eff_novelty_coef": 0.047045000000000003
            },
            {
              "gen": 4,
              "best": 0.0,
              "mean": -146.53333333333333,
              "num_species": 4,
              "avg_complexity": 6.0,
              "max_complexity": 6,
              "archive_size": 5,
              "avg_mut_rate": 0.5,
              "eff_novelty_coef": 0.04563365
            },
            {
              "gen": 5,
              "best": 0.0,
              "mean": -117.83333333333334,
              "num_species": 5,
              "avg_complexity": 6.05,
              "max_complexity": 8,
              "archive_size": 5,
              "avg_mut_rate": 0.5,
              "eff_novelty_coef": 0.0442646405
            },
            {
              "gen": 6,
              "best": 0.0,
              "mean": -147.025,
              "num_species": 5,
              "avg_complexity": 6.05,
              "max_complexity": 8,
              "archive_size": 5,
              "avg_mut_rate": 0.5,
              "eff_novelty_coef": 0.042936701285
            },
            {
              "gen": 7,
              "best": 0.0,
              "mean": -125.90833333333335,
              "num_species": 9,
              "avg_complexity": 6.225,
              "max_complexity": 8,
              "archive_size": 5,
              "avg_mut_rate": 0.5,
              "eff_novelty_coef": 0.04164860024644999
            },
            {
              "gen": 8,
              "best": 0.0,
              "mean": -116.10833333333332,
              "num_species": 5,
              "avg_complexity": 6.1,
              "max_complexity": 8,
              "archive_size": 5,
              "avg_mut_rate": 0.5,
              "eff_novelty_coef": 0.040399142239056496
            },
            {
              "gen": 9,
              "best": 0.0,
              "mean": -139.74166666666665,
              "num_species": 5,
              "avg_complexity": 6.2,
              "max_complexity": 9,
              "archive_size": 5,
              "avg_mut_rate": 0.5,
              "eff_novelty_coef": 0.0391871679718848
            },
            {
              "gen": 10,
              "best": 0.0,
              "mean": -111.76666666666668,
              "num_species": 5,
              "avg_complexity": 6.125,
              "max_complexity": 9,
              "archive_size": 5,
              "avg_mut_rate": 0.5,
              "eff_novelty_coef": 0.03801155293272826
            },
            {
              "gen": 11,
              "best": 0.0,
              "mean": -122.075,
              "num_species": 4,
              "avg_complexity": 6.15,
              "max_complexity": 8,
              "archive_size": 5,
              "avg_mut_rate": 0.5,
              "eff_novelty_coef": 0.03687120634474641
            },
            {
              "gen": 12,
              "best": 0.0,
              "mean": -116.94166666666668,
              "num_species": 5,
              "avg_complexity": 6.05,
              "max_complexity": 8,
              "archive_size": 5,
              "avg_mut_rate": 0.5,
              "eff_novelty_coef": 0.03576507015440401
            },
            {
              "gen": 13,
              "best": 0.0,
              "mean": -99.89166666666665,
              "num_species": 5,
              "avg_complexity": 6.05,
              "max_complexity": 8,
              "archive_size": 5,
              "avg_mut_rate": 0.5,
              "eff_novelty_coef": 0.03469211804977189
            },
            {
              "gen": 14,
              "best": 0.0,
              "mean": -135.18333333333334,
              "num_species": 5,
              "avg_complexity": 6.05,
              "max_complexity": 8,
              "archive_size": 5,
              "avg_mut_rate": 0.5,
              "eff_novelty_coef": 0.03365135450827873
            },
            {
              "gen": 15,
              "best": 0.0,
              "mean": -117.45833333333334,
              "num_species": 5,
              "avg_complexity": 6.0,
              "max_complexity": 6,
              "archive_size": 5,
              "avg_mut_rate": 0.5,
              "eff_novelty_coef": 0.03264181387303037
            },
            {
              "gen": 16,
              "best": 0.0,
              "mean": -140.84166666666667,
              "num_species": 7,
              "avg_complexity": 6.0,
              "max_complexity": 6,
              "archive_size": 5,
              "avg_mut_rate": 0.5,
              "eff_novelty_coef": 0.031662559456839455
            },
            {
              "gen": 17,
              "best": 0.0,
              "mean": -133.65833333333336,
              "num_species": 8,
              "avg_complexity": 6.0,
              "max_complexity": 6,
              "archive_size": 5,
              "avg_mut_rate": 0.5,
              "eff_novelty_coef": 0.030712682673134276
            },
            {
              "gen": 18,
              "best": 0.0,
              "mean": -122.73333333333335,
              "num_species": 6,
              "avg_complexity": 6.1,
              "max_complexity": 8,
              "archive_size": 5,
              "avg_mut_rate": 0.5,
              "eff_novelty_coef": 0.029791302192940246
            },
            {
              "gen": 19,
              "best": 0.0,
              "mean": -113.51666666666665,
              "num_species": 5,
              "avg_complexity": 6.175,
              "max_complexity": 8,
              "archive_size": 5,
              "avg_mut_rate": 0.5,
              "eff_novelty_coef": 0.02889756312715204
            },
            {
              "gen": 20,
              "best": 0.0,
              "mean": -118.15,
              "num_species": 6,
              "avg_complexity": 6.15,
              "max_complexity": 8,
              "archive_size": 5,
              "avg_mut_rate": 0.5,
              "eff_novelty_coef": 0.028030636233337475
            },
            {
              "gen": 21,
              "best": 0.0,
              "mean": -102.26666666666668,
              "num_species": 7,
              "avg_complexity": 6.75,
              "max_complexity": 10,
              "archive_size": 5,
              "avg_mut_rate": 0.5,
              "eff_novelty_coef": 0.02718971714633735
            },
            {
              "gen": 22,
              "best": 0.0,
              "mean": -129.68333333333334,
              "num_species": 5,
              "avg_complexity": 6.6,
              "max_complexity": 9,
              "archive_size": 5,
              "avg_mut_rate": 0.5,
              "eff_novelty_coef": 0.02637402563194723
            },
            {
              "gen": 23,
              "best": 0.0,
              "mean": -131.23333333333332,
              "num_species": 6,
              "avg_complexity": 7.075,
              "max_complexity": 10,
              "archive_size": 5,
              "avg_mut_rate": 0.5,
              "eff_novelty_coef": 0.025582804862988813
            },
            {
              "gen": 24,
              "best": 0.0,
              "mean": -137.28333333333333,
              "num_species": 8,
              "avg_complexity": 6.3,
              "max_complexity": 8,
              "archive_size": 5,
              "avg_mut_rate": 0.5,
              "eff_novelty_coef": 0.024815320717099146
            },
            {
              "gen": 25,
              "best": 0.0,
              "mean": -131.4,
              "num_species": 5,
              "avg_complexity": 6.875,
              "max_complexity": 9,
              "archive_size": 5,
              "avg_mut_rate": 0.5,
              "eff_novelty_coef": 0.02407086109558617
            }
          ],
          "elapsed_s": 12.087039232254028,
          "final_best_fitness": -195.05,
          "final_best_std": 14.850841726986387,
          "final_best_min": -200.0,
          "final_best_max": -150.0,
          "final_best_evals": [
            -200.0,
            -200.0,
            -200.0,
            -200.0,
            -150.0,
            -200.0,
            -200.0,
            -151.0,
            -200.0,
            -200.0,
            -200.0,
            -200.0,
            -200.0,
            -200.0,
            -200.0,
            -200.0,
            -200.0,
            -200.0,
            -200.0,
            -200.0
          ],
          "final_best_complexity": 8,
          "final_best_hidden": 1,
          "first_solve_gen": 1,
          "best_ever_training_score": -1000000000.0
        },
        {
          "seed": 2,
          "history": [
            {
              "gen": 1,
              "best": 0.0,
              "mean": -155.0,
              "num_species": 3,
              "avg_complexity": 6.0,
              "max_complexity": 6,
              "archive_size": 3,
              "avg_mut_rate": 0.5,
              "eff_novelty_coef": 0.05
            },
            {
              "gen": 2,
              "best": 0.0,
              "mean": -160.0,
              "num_species": 3,
              "avg_complexity": 6.0,
              "max_complexity": 6,
              "archive_size": 6,
              "avg_mut_rate": 0.5,
              "eff_novelty_coef": 0.0485
            },
            {
              "gen": 3,
              "best": 0.0,
              "mean": -129.875,
              "num_species": 5,
              "avg_complexity": 6.05,
              "max_complexity": 8,
              "archive_size": 7,
              "avg_mut_rate": 0.5,
              "eff_novelty_coef": 0.047045000000000003
            },
            {
              "gen": 4,
              "best": 0.0,
              "mean": -105.19166666666665,
              "num_species": 6,
              "avg_complexity": 6.05,
              "max_complexity": 8,
              "archive_size": 7,
              "avg_mut_rate": 0.5,
              "eff_novelty_coef": 0.04563365
            },
            {
              "gen": 5,
              "best": 0.0,
              "mean": -108.10833333333332,
              "num_species": 5,
              "avg_complexity": 5.975,
              "max_complexity": 8,
              "archive_size": 7,
              "avg_mut_rate": 0.5,
              "eff_novelty_coef": 0.0442646405
            },
            {
              "gen": 6,
              "best": 0.0,
              "mean": -123.94166666666668,
              "num_species": 6,
              "avg_complexity": 6.35,
              "max_complexity": 8,
              "archive_size": 7,
              "avg_mut_rate": 0.5,
              "eff_novelty_coef": 0.042936701285
            },
            {
              "gen": 7,
              "best": 0.0,
              "mean": -142.55833333333334,
              "num_species": 5,
              "avg_complexity": 6.25,
              "max_complexity": 8,
              "archive_size": 7,
              "avg_mut_rate": 0.5,
              "eff_novelty_coef": 0.04164860024644999
            },
            {
              "gen": 8,
              "best": 0.0,
              "mean": -137.22500000000002,
              "num_species": 6,
              "avg_complexity": 6.275,
              "max_complexity": 9,
              "archive_size": 7,
              "avg_mut_rate": 0.5,
              "eff_novelty_coef": 0.040399142239056496
            },
            {
              "gen": 9,
              "best": 0.0,
              "mean": -109.4,
              "num_species": 8,
              "avg_complexity": 6.2,
              "max_complexity": 8,
              "archive_size": 7,
              "avg_mut_rate": 0.5,
              "eff_novelty_coef": 0.0391871679718848
            },
            {
              "gen": 10,
              "best": 0.0,
              "mean": -117.53333333333335,
              "num_species": 5,
              "avg_complexity": 6.075,
              "max_complexity": 8,
              "archive_size": 7,
              "avg_mut_rate": 0.5,
              "eff_novelty_coef": 0.03801155293272826
            },
            {
              "gen": 11,
              "best": 0.0,
              "mean": -132.69166666666666,
              "num_species": 6,
              "avg_complexity": 6.275,
              "max_complexity": 8,
              "archive_size": 7,
              "avg_mut_rate": 0.5,
              "eff_novelty_coef": 0.03687120634474641
            },
            {
              "gen": 12,
              "best": 0.0,
              "mean": -110.49166666666665,
              "num_species": 7,
              "avg_complexity": 6.275,
              "max_complexity": 8,
              "archive_size": 7,
              "avg_mut_rate": 0.5,
              "eff_novelty_coef": 0.03576507015440401
            },
            {
              "gen": 13,
              "best": 0.0,
              "mean": -133.78333333333336,
              "num_species": 6,
              "avg_complexity": 6.425,
              "max_complexity": 8,
              "archive_size": 7,
              "avg_mut_rate": 0.5,
              "eff_novelty_coef": 0.03469211804977189
            },
            {
              "gen": 14,
              "best": 0.0,
              "mean": -122.01666666666668,
              "num_species": 7,
              "avg_complexity": 6.25,
              "max_complexity": 8,
              "archive_size": 7,
              "avg_mut_rate": 0.5,
              "eff_novelty_coef": 0.03365135450827873
            },
            {
              "gen": 15,
              "best": 0.0,
              "mean": -108.39166666666665,
              "num_species": 5,
              "avg_complexity": 6.675,
              "max_complexity": 10,
              "archive_size": 7,
              "avg_mut_rate": 0.5,
              "eff_novelty_coef": 0.03264181387303037
            },
            {
              "gen": 16,
              "best": 0.0,
              "mean": -118.45,
              "num_species": 5,
              "avg_complexity": 6.5,
              "max_complexity": 10,
              "archive_size": 7,
              "avg_mut_rate": 0.5,
              "eff_novelty_coef": 0.031662559456839455
            },
            {
              "gen": 17,
              "best": 0.0,
              "mean": -141.21666666666664,
              "num_species": 5,
              "avg_complexity": 6.05,
              "max_complexity": 8,
              "archive_size": 7,
              "avg_mut_rate": 0.5,
              "eff_novelty_coef": 0.030712682673134276
            },
            {
              "gen": 18,
              "best": 0.0,
              "mean": -118.13333333333333,
              "num_species": 6,
              "avg_complexity": 6.05,
              "max_complexity": 8,
              "archive_size": 7,
              "avg_mut_rate": 0.5,
              "eff_novelty_coef": 0.029791302192940246
            },
            {
              "gen": 19,
              "best": 0.0,
              "mean": -125.00833333333335,
              "num_species": 6,
              "avg_complexity": 6.125,
              "max_complexity": 8,
              "archive_size": 7,
              "avg_mut_rate": 0.5,
              "eff_novelty_coef": 0.02889756312715204
            },
            {
              "gen": 20,
              "best": 0.0,
              "mean": -95.75,
              "num_species": 6,
              "avg_complexity": 5.7,
              "max_complexity": 9,
              "archive_size": 7,
              "avg_mut_rate": 0.5,
              "eff_novelty_coef": 0.028030636233337475
            },
            {
              "gen": 21,
              "best": 0.0,
              "mean": -110.34166666666665,
              "num_species": 6,
              "avg_complexity": 5.85,
              "max_complexity": 10,
              "archive_size": 7,
              "avg_mut_rate": 0.5,
              "eff_novelty_coef": 0.02718971714633735
            },
            {
              "gen": 22,
              "best": 0.0,
              "mean": -126.025,
              "num_species": 7,
              "avg_complexity": 6.25,
              "max_complexity": 10,
              "archive_size": 7,
              "avg_mut_rate": 0.5,
              "eff_novelty_coef": 0.02637402563194723
            },
            {
              "gen": 23,
              "best": 0.0,
              "mean": -126.95833333333334,
              "num_species": 6,
              "avg_complexity": 6.075,
              "max_complexity": 9,
              "archive_size": 7,
              "avg_mut_rate": 0.5,
              "eff_novelty_coef": 0.025582804862988813
            },
            {
              "gen": 24,
              "best": 0.0,
              "mean": -120.95833333333334,
              "num_species": 7,
              "avg_complexity": 5.8,
              "max_complexity": 10,
              "archive_size": 7,
              "avg_mut_rate": 0.5,
              "eff_novelty_coef": 0.024815320717099146
            },
            {
              "gen": 25,
              "best": 0.0,
              "mean": -124.65,
              "num_species": 4,
              "avg_complexity": 5.325,
              "max_complexity": 10,
              "archive_size": 7,
              "avg_mut_rate": 0.5,
              "eff_novelty_coef": 0.02407086109558617
            }
          ],
          "elapsed_s": 12.45326042175293,
          "final_best_fitness": -120.1,
          "final_best_std": 3.766961640367472,
          "final_best_min": -125.0,
          "final_best_max": -114.0,
          "final_best_evals": [
            -122.0,
            -122.0,
            -122.0,
            -122.0,
            -125.0,
            -116.0,
            -115.0,
            -124.0,
            -122.0,
            -122.0,
            -114.0,
            -122.0,
            -114.0,
            -123.0,
            -114.0,
            -122.0,
            -114.0,
            -122.0,
            -123.0,
            -122.0
          ],
          "final_best_complexity": 6,
          "final_best_hidden": 0,
          "first_solve_gen": 1,
          "best_ever_training_score": -1000000000.0
        }
      ],
      "mean_final": -171.66666666666666,
      "std_final": 36.51575763359643,
      "mean_time": 12.337708791097006,
      "mean_complexity": 6.333333333333333,
      "solve_rate": 1.0
    }
  }
}