{
  "env": "MountainCar-v0",
  "gens": 60,
  "n_seeds": 3,
  "pop_size": 60,
  "tag": "round4_mountaincar",
  "algos": {
    "crit": {
      "runs": [
        {
          "seed": 0,
          "history": [
            {
              "gen": 1,
              "best": -200.0,
              "mean": -200.0,
              "num_species": 3,
              "avg_complexity": 6.033333333333333,
              "max_complexity": 8,
              "archive_size": 3,
              "avg_mut_rate": 0.42583333333333334,
              "eff_novelty_coef": 0.05
            },
            {
              "gen": 2,
              "best": -200.0,
              "mean": -200.0,
              "num_species": 5,
              "avg_complexity": 6.066666666666666,
              "max_complexity": 8,
              "archive_size": 8,
              "avg_mut_rate": 0.35486111111111107,
              "eff_novelty_coef": 0.0485
            },
            {
              "gen": 3,
              "best": -200.0,
              "mean": -200.0,
              "num_species": 4,
              "avg_complexity": 6.133333333333334,
              "max_complexity": 8,
              "archive_size": 8,
              "avg_mut_rate": 0.2978395061728395,
              "eff_novelty_coef": 0.047045000000000003
            },
            {
              "gen": 4,
              "best": -200.0,
              "mean": -200.0,
              "num_species": 4,
              "avg_complexity": 6.266666666666667,
              "max_complexity": 8,
              "archive_size": 8,
              "avg_mut_rate": 0.26941872427983543,
              "eff_novelty_coef": 0.04563365
            },
            {
              "gen": 5,
              "best": -189.0,
              "mean": -199.45,
              "num_species": 4,
              "avg_complexity": 6.1,
              "max_complexity": 8,
              "archive_size": 8,
              "avg_mut_rate": 0.2230420524691358,
              "eff_novelty_coef": 0.0442646405
            },
            {
              "gen": 6,
              "best": -171.0,
              "mean": -194.58333333333334,
              "num_species": 4,
              "avg_complexity": 6.6,
              "max_complexity": 8,
              "archive_size": 8,
              "avg_mut_rate": 0.22143007687471428,
              "eff_novelty_coef": 0.042936701285
            },
            {
              "gen": 7,
              "best": -142.0,
              "mean": -182.76666666666668,
              "num_species": 4,
              "avg_complexity": 7.25,
              "max_complexity": 9,
              "archive_size": 8,
              "avg_mut_rate": 0.3093839603814207,
              "eff_novelty_coef": 0.04164860024644999
            },
            {
              "gen": 8,
              "best": -169.0,
              "mean": -189.81666666666666,
              "num_species": 8,
              "avg_complexity": 7.866666666666666,
              "max_complexity": 9,
              "archive_size": 8,
              "avg_mut_rate": 0.4616284019680688,
              "eff_novelty_coef": 0.040399142239056496
            },
            {
              "gen": 9,
              "best": -140.0,
              "mean": -181.28333333333333,
              "num_species": 6,
              "avg_complexity": 8.05,
              "max_complexity": 10,
              "archive_size": 8,
              "avg_mut_rate": 0.5580752791444924,
              "eff_novelty_coef": 0.0391871679718848
            },
            {
              "gen": 10,
              "best": -136.0,
              "mean": -172.15,
              "num_species": 14,
              "avg_complexity": 8.283333333333333,
              "max_complexity": 10,
              "archive_size": 8,
              "avg_mut_rate": 0.7093458798574152,
              "eff_novelty_coef": 0.03801155293272826
            },
            {
              "gen": 11,
              "best": -146.0,
              "mean": -183.8,
              "num_species": 4,
              "avg_complexity": 8.25,
              "max_complexity": 10,
              "archive_size": 8,
              "avg_mut_rate": 0.8287999999999999,
              "eff_novelty_coef": 0.03687120634474641
            },
            {
              "gen": 12,
              "best": -140.0,
              "mean": -174.58333333333334,
              "num_species": 5,
              "avg_complexity": 8.45,
              "max_complexity": 12,
              "archive_size": 8,
              "avg_mut_rate": 0.9839999999999999,
              "eff_novelty_coef": 0.03576507015440401
            },
            {
              "gen": 13,
              "best": -140.0,
              "mean": -179.11666666666667,
              "num_species": 9,
              "avg_complexity": 8.3,
              "max_complexity": 10,
              "archive_size": 8,
              "avg_mut_rate": 1.1998079999999995,
              "eff_novelty_coef": 0.03469211804977189
            },
            {
              "gen": 14,
              "best": -114.0,
              "mean": -180.01666666666668,
              "num_species": 12,
              "avg_complexity": 8.8,
              "max_complexity": 11,
              "archive_size": 8,
              "avg_mut_rate": 1.2746111999999998,
              "eff_novelty_coef": 0.03365135450827873
            },
            {
              "gen": 15,
              "best": -144.0,
              "mean": -186.16666666666666,
              "num_species": 5,
              "avg_complexity": 9.1,
              "max_complexity": 12,
              "archive_size": 8,
              "avg_mut_rate": 1.2667759999999997,
              "eff_novelty_coef": 0.03264181387303037
            },
            {
              "gen": 16,
              "best": -143.0,
              "mean": -192.2,
              "num_species": 12,
              "avg_complexity": 9.183333333333334,
              "max_complexity": 11,
              "archive_size": 8,
              "avg_mut_rate": 1.1240266666666665,
              "eff_novelty_coef": 0.031662559456839455
            },
            {
              "gen": 17,
              "best": -115.0,
              "mean": -180.08333333333334,
              "num_species": 11,
              "avg_complexity": 9.15,
              "max_complexity": 12,
              "archive_size": 8,
              "avg_mut_rate": 1.302188888888889,
              "eff_novelty_coef": 0.030712682673134276
            },
            {
              "gen": 18,
              "best": -142.0,
              "mean": -186.35,
              "num_species": 7,
              "avg_complexity": 9.533333333333333,
              "max_complexity": 12,
              "archive_size": 8,
              "avg_mut_rate": 1.423148148148148,
              "eff_novelty_coef": 0.029791302192940246
            },
            {
              "gen": 19,
              "best": -112.0,
              "mean": -180.6,
              "num_species": 5,
              "avg_complexity": 9.7,
              "max_complexity": 12,
              "archive_size": 8,
              "avg_mut_rate": 1.4583333333333333,
              "eff_novelty_coef": 0.02889756312715204
            },
            {
              "gen": 20,
              "best": -144.0,
              "mean": -177.48333333333332,
              "num_species": 8,
              "avg_complexity": 9.416666666666666,
              "max_complexity": 13,
              "archive_size": 8,
              "avg_mut_rate": 1.3881944444444443,
              "eff_novelty_coef": 0.028030636233337475
            },
            {
              "gen": 21,
              "best": -142.0,
              "mean": -186.25,
              "num_species": 5,
              "avg_complexity": 10.15,
              "max_complexity": 14,
              "archive_size": 8,
              "avg_mut_rate": 1.4694444444444446,
              "eff_novelty_coef": 0.02718971714633735
            },
            {
              "gen": 22,
              "best": -139.0,
              "mean": -181.73333333333332,
              "num_species": 4,
              "avg_complexity": 10.283333333333333,
              "max_complexity": 14,
              "archive_size": 8,
              "avg_mut_rate": 1.4333333333333333,
              "eff_novelty_coef": 0.02637402563194723
            },
            {
              "gen": 23,
              "best": -141.0,
              "mean": -178.46666666666667,
              "num_species": 9,
              "avg_complexity": 10.216666666666667,
              "max_complexity": 15,
              "archive_size": 8,
              "avg_mut_rate": 1.4694444444444443,
              "eff_novelty_coef": 0.025582804862988813
            },
            {
              "gen": 24,
              "best": -139.0,
              "mean": -179.48333333333332,
              "num_species": 11,
              "avg_complexity": 8.983333333333333,
              "max_complexity": 15,
              "archive_size": 8,
              "avg_mut_rate": 1.4166666666666667,
              "eff_novelty_coef": 0.024815320717099146
            },
            {
              "gen": 25,
              "best": -133.0,
              "mean": -184.46666666666667,
              "num_species": 11,
              "avg_complexity": 8.583333333333334,
              "max_complexity": 11,
              "archive_size": 8,
              "avg_mut_rate": 1.3472222222222223,
              "eff_novelty_coef": 0.02407086109558617
            },
            {
              "gen": 26,
              "best": -126.0,
              "mean": -175.36666666666667,
              "num_species": 6,
              "avg_complexity": 8.9,
              "max_complexity": 12,
              "archive_size": 8,
              "avg_mut_rate": 1.378009259259259,
              "eff_novelty_coef": 0.023348735262718585
            },
            {
              "gen": 27,
              "best": -154.0,
              "mean": -186.2,
              "num_species": 4,
              "avg_complexity": 9.566666666666666,
              "max_complexity": 12,
              "archive_size": 8,
              "avg_mut_rate": 1.4047260802469135,
              "eff_novelty_coef": 0.022648273204837026
            },
            {
              "gen": 28,
              "best": -150.0,
              "mean": -190.7,
              "num_species": 5,
              "avg_complexity": 9.666666666666666,
              "max_complexity": 12,
              "archive_size": 8,
              "avg_mut_rate": 1.3188496656378603,
              "eff_novelty_coef": 0.021968825008691916
            },
            {
              "gen": 29,
              "best": -88.0,
              "mean": -172.56666666666666,
              "num_species": 7,
              "avg_complexity": 9.4,
              "max_complexity": 12,
              "archive_size": 8,
              "avg_mut_rate": 1.109154771090535,
              "eff_novelty_coef": 0.02130976025843116
            },
            {
              "gen": 30,
              "best": -91.0,
              "mean": -162.48333333333332,
              "num_species": 5,
              "avg_complexity": 9.916666666666666,
              "max_complexity": 13,
              "archive_size": 8,
              "avg_mut_rate": 1.1920578275034293,
              "eff_novelty_coef": 0.020670467450678222
            },
            {
              "gen": 31,
              "best": -94.0,
              "mean": -167.08333333333334,
              "num_species": 5,
              "avg_complexity": 10.333333333333334,
              "max_complexity": 13,
              "archive_size": 8,
              "avg_mut_rate": 1.0941716291104635,
              "eff_novelty_coef": 0.020050353427157875
            },
            {
              "gen": 32,
              "best": -88.0,
              "mean": -166.4,
              "num_species": 4,
              "avg_complexity": 10.4,
              "max_complexity": 13,
              "archive_size": 8,
              "avg_mut_rate": 1.2998842592592592,
              "eff_novelty_coef": 0.01944884282434314
            },
            {
              "gen": 33,
              "best": -177.0,
              "mean": -192.46666666666667,
              "num_species": 6,
              "avg_complexity": 11.016666666666667,
              "max_complexity": 14,
              "archive_size": 8,
              "avg_mut_rate": 1.3196759259259259,
              "eff_novelty_coef": 0.018865377539612843
            },
            {
              "gen": 34,
              "best": -181.0,
              "mean": -195.25,
              "num_species": 5,
              "avg_complexity": 11.033333333333333,
              "max_complexity": 15,
              "archive_size": 8,
              "avg_mut_rate": 1.0962577160493827,
              "eff_novelty_coef": 0.018299416213424458
            },
            {
              "gen": 35,
              "best": -155.0,
              "mean": -189.66666666666666,
              "num_species": 5,
              "avg_complexity": 11.35,
              "max_complexity": 15,
              "archive_size": 8,
              "avg_mut_rate": 1.0049832818930045,
              "eff_novelty_coef": 0.017750433727021724
            },
            {
              "gen": 36,
              "best": -154.0,
              "mean": -183.4,
              "num_species": 6,
              "avg_complexity": 11.05,
              "max_complexity": 13,
              "archive_size": 8,
              "avg_mut_rate": 1.1918861811271146,
              "eff_novelty_coef": 0.017217920715211072
            },
            {
              "gen": 37,
              "best": -127.0,
              "mean": -180.56666666666666,
              "num_species": 5,
              "avg_complexity": 10.866666666666667,
              "max_complexity": 13,
              "archive_size": 8,
              "avg_mut_rate": 1.178243955761317,
              "eff_novelty_coef": 0.016701383093754737
            },
            {
              "gen": 38,
              "best": -107.0,
              "mean": -166.73333333333332,
              "num_species": 4,
              "avg_complexity": 10.95,
              "max_complexity": 13,
              "archive_size": 8,
              "avg_mut_rate": 1.270601851851852,
              "eff_novelty_coef": 0.016200341600942095
            },
            {
              "gen": 39,
              "best": -154.0,
              "mean": -184.53333333333333,
              "num_species": 6,
              "avg_complexity": 11.0,
              "max_complexity": 14,
              "archive_size": 8,
              "avg_mut_rate": 1.2780092592592596,
              "eff_novelty_coef": 0.01571433135291383
            },
            {
              "gen": 40,
              "best": -154.0,
              "mean": -182.86666666666667,
              "num_species": 6,
              "avg_complexity": 11.116666666666667,
              "max_complexity": 13,
              "archive_size": 8,
              "avg_mut_rate": 1.4125,
              "eff_novelty_coef": 0.015242901412326416
            },
            {
              "gen": 41,
              "best": -86.0,
              "mean": -171.5,
              "num_species": 5,
              "avg_complexity": 11.416666666666666,
              "max_complexity": 14,
              "archive_size": 8,
              "avg_mut_rate": 1.4159722222222224,
              "eff_novelty_coef": 0.014785614369956623
            },
            {
              "gen": 42,
              "best": -88.0,
              "mean": -172.0,
              "num_species": 5,
              "avg_complexity": 11.466666666666667,
              "max_complexity": 16,
              "archive_size": 8,
              "avg_mut_rate": 1.2883101851851853,
              "eff_novelty_coef": 0.014342045938857927
            },
            {
              "gen": 43,
              "best": -100.0,
              "mean": -169.86666666666667,
              "num_species": 5,
              "avg_complexity": 11.216666666666667,
              "max_complexity": 15,
              "archive_size": 8,
              "avg_mut_rate": 1.1472029320987656,
              "eff_novelty_coef": 0.013911784560692187
            },
            {
              "gen": 44,
              "best": -160.0,
              "mean": -191.33333333333334,
              "num_species": 6,
              "avg_complexity": 10.983333333333333,
              "max_complexity": 15,
              "archive_size": 8,
              "avg_mut_rate": 1.2161844135802473,
              "eff_novelty_coef": 0.01349443102387142
            },
            {
              "gen": 45,
              "best": -96.0,
              "mean": -172.3,
              "num_species": 6,
              "avg_complexity": 11.25,
              "max_complexity": 15,
              "archive_size": 8,
              "avg_mut_rate": 1.1270302854938274,
              "eff_novelty_coef": 0.013089598093155278
            },
            {
              "gen": 46,
              "best": -91.0,
              "mean": -173.53333333333333,
              "num_species": 7,
              "avg_complexity": 11.266666666666667,
              "max_complexity": 14,
              "archive_size": 8,
              "avg_mut_rate": 1.1493734282121628,
              "eff_novelty_coef": 0.012696910150360619
            },
            {
              "gen": 47,
              "best": -117.0,
              "mean": -177.56666666666666,
              "num_species": 6,
              "avg_complexity": 10.75,
              "max_complexity": 12,
              "archive_size": 8,
              "avg_mut_rate": 1.3164351851851854,
              "eff_novelty_coef": 0.0123160028458498
            },
            {
              "gen": 48,
              "best": -155.0,
              "mean": -190.25,
              "num_species": 6,
              "avg_complexity": 10.85,
              "max_complexity": 13,
              "archive_size": 8,
              "avg_mut_rate": 1.2571180555555557,
              "eff_novelty_coef": 0.011946522760474306
            },
            {
              "gen": 49,
              "best": -87.0,
              "mean": -172.33333333333334,
              "num_species": 7,
              "avg_complexity": 10.816666666666666,
              "max_complexity": 13,
              "archive_size": 8,
              "avg_mut_rate": 1.298694701646091,
              "eff_novelty_coef": 0.011588127077660076
            },
            {
              "gen": 50,
              "best": -91.0,
              "mean": -173.53333333333333,
              "num_species": 7,
              "avg_complexity": 10.816666666666666,
              "max_complexity": 13,
              "archive_size": 8,
              "avg_mut_rate": 1.4291666666666667,
              "eff_novelty_coef": 0.011240483265330274
            },
            {
              "gen": 51,
              "best": -87.0,
              "mean": -166.1,
              "num_species": 4,
              "avg_complexity": 10.9,
              "max_complexity": 14,
              "archive_size": 8,
              "avg_mut_rate": 1.3055555555555558,
              "eff_novelty_coef": 0.010903268767370366
            },
            {
              "gen": 52,
              "best": -156.0,
              "mean": -186.8,
              "num_species": 4,
              "avg_complexity": 10.783333333333333,
              "max_complexity": 12,
              "archive_size": 8,
              "avg_mut_rate": 1.2953703703703705,
              "eff_novelty_coef": 0.010576170704349255
            },
            {
              "gen": 53,
              "best": -136.0,
              "mean": -184.0,
              "num_species": 5,
              "avg_complexity": 11.066666666666666,
              "max_complexity": 14,
              "archive_size": 8,
              "avg_mut_rate": 1.251658950617284,
              "eff_novelty_coef": 0.010258885583218776
            },
            {
              "gen": 54,
              "best": -153.0,
              "mean": -185.85,
              "num_species": 6,
              "avg_complexity": 11.433333333333334,
              "max_complexity": 14,
              "archive_size": 8,
              "avg_mut_rate": 1.1580632716049386,
              "eff_novelty_coef": 0.009951119015722213
            },
            {
              "gen": 55,
              "best": -125.0,
              "mean": -181.58333333333334,
              "num_species": 6,
              "avg_complexity": 11.25,
              "max_complexity": 13,
              "archive_size": 8,
              "avg_mut_rate": 1.1049409507887518,
              "eff_novelty_coef": 0.009652585445250546
            },
            {
              "gen": 56,
              "best": -157.0,
              "mean": -191.4,
              "num_species": 7,
              "avg_complexity": 11.55,
              "max_complexity": 14,
              "archive_size": 8,
              "avg_mut_rate": 1.2900875557270235,
              "eff_novelty_coef": 0.009363007881893029
            },
            {
              "gen": 57,
              "best": -155.0,
              "mean": -188.75,
              "num_species": 5,
              "avg_complexity": 11.766666666666667,
              "max_complexity": 14,
              "archive_size": 8,
              "avg_mut_rate": 1.0683729941843851,
              "eff_novelty_coef": 0.009082117645436238
            },
            {
              "gen": 58,
              "best": -97.0,
              "mean": -173.03333333333333,
              "num_species": 6,
              "avg_complexity": 11.716666666666667,
              "max_complexity": 13,
              "archive_size": 8,
              "avg_mut_rate": 1.127522679787126,
              "eff_novelty_coef": 0.00880965411607315
            },
            {
              "gen": 59,
              "best": -137.0,
              "mean": -170.4,
              "num_species": 4,
              "avg_complexity": 11.516666666666667,
              "max_complexity": 14,
              "archive_size": 8,
              "avg_mut_rate": 1.378779585383405,
              "eff_novelty_coef": 0.008545364492590956
            },
            {
              "gen": 60,
              "best": -135.0,
              "mean": -180.6,
              "num_species": 7,
              "avg_complexity": 11.516666666666667,
              "max_complexity": 14,
              "archive_size": 8,
              "avg_mut_rate": 1.4059274322639486,
              "eff_novelty_coef": 0.008289003557813228
            }
          ],
          "elapsed_s": 37.86954426765442,
          "final_best_fitness": -172.4,
          "final_best_std": 22.30560467685196,
          "final_best_min": -200.0,
          "final_best_max": -138.0,
          "final_best_evals": [
            -200.0,
            -168.0,
            -172.0,
            -169.0,
            -163.0,
            -177.0,
            -143.0,
            -164.0,
            -184.0,
            -200.0,
            -142.0,
            -200.0,
            -138.0,
            -200.0,
            -141.0,
            -200.0,
            -140.0,
            -177.0,
            -200.0,
            -170.0
          ],
          "final_best_complexity": 11,
          "final_best_hidden": 4,
          "first_solve_gen": null
        },
        {
          "seed": 1,
          "history": [
            {
              "gen": 1,
              "best": -163.0,
              "mean": -192.6,
              "num_species": 5,
              "avg_complexity": 6.033333333333333,
              "max_complexity": 8,
              "archive_size": 5,
              "avg_mut_rate": 0.483888888888889,
              "eff_novelty_coef": 0.05
            },
            {
              "gen": 2,
              "best": -162.0,
              "mean": -188.6,
              "num_species": 4,
              "avg_complexity": 6.1,
              "max_complexity": 8,
              "archive_size": 5,
              "avg_mut_rate": 0.4444907407407407,
              "eff_novelty_coef": 0.0485
            },
            {
              "gen": 3,
              "best": -160.0,
              "mean": -190.18333333333334,
              "num_species": 5,
              "avg_complexity": 6.033333333333333,
              "max_complexity": 8,
              "archive_size": 5,
              "avg_mut_rate": 0.444591049382716,
              "eff_novelty_coef": 0.047045000000000003
            },
            {
              "gen": 4,
              "best": -160.0,
              "mean": -190.01666666666668,
              "num_species": 5,
              "avg_complexity": 6.0,
              "max_complexity": 6,
              "archive_size": 5,
              "avg_mut_rate": 0.585861111111111,
              "eff_novelty_coef": 0.04563365
            },
            {
              "gen": 5,
              "best": -170.0,
              "mean": -191.58333333333334,
              "num_species": 5,
              "avg_complexity": 6.066666666666666,
              "max_complexity": 8,
              "archive_size": 5,
              "avg_mut_rate": 0.754247839506173,
              "eff_novelty_coef": 0.0442646405
            },
            {
              "gen": 6,
              "best": -146.0,
              "mean": -187.1,
              "num_species": 5,
              "avg_complexity": 6.116666666666666,
              "max_complexity": 9,
              "archive_size": 5,
              "avg_mut_rate": 0.8909265329218108,
              "eff_novelty_coef": 0.042936701285
            },
            {
              "gen": 7,
              "best": -119.0,
              "mean": -176.66666666666666,
              "num_species": 4,
              "avg_complexity": 6.166666666666667,
              "max_complexity": 8,
              "archive_size": 5,
              "avg_mut_rate": 1.0605639190672151,
              "eff_novelty_coef": 0.04164860024644999
            },
            {
              "gen": 8,
              "best": -116.0,
              "mean": -170.35,
              "num_species": 8,
              "avg_complexity": 6.166666666666667,
              "max_complexity": 8,
              "archive_size": 5,
              "avg_mut_rate": 1.222396515306356,
              "eff_novelty_coef": 0.040399142239056496
            },
            {
              "gen": 9,
              "best": -127.0,
              "mean": -187.36666666666667,
              "num_species": 10,
              "avg_complexity": 6.283333333333333,
              "max_complexity": 9,
              "archive_size": 5,
              "avg_mut_rate": 1.2066284019680689,
              "eff_novelty_coef": 0.0391871679718848
            },
            {
              "gen": 10,
              "best": -130.0,
              "mean": -183.75,
              "num_species": 7,
              "avg_complexity": 6.166666666666667,
              "max_complexity": 9,
              "archive_size": 5,
              "avg_mut_rate": 1.1488378692907588,
              "eff_novelty_coef": 0.03801155293272826
            },
            {
              "gen": 11,
              "best": -116.0,
              "mean": -172.33333333333334,
              "num_species": 6,
              "avg_complexity": 6.15,
              "max_complexity": 9,
              "archive_size": 5,
              "avg_mut_rate": 1.0135670602023847,
              "eff_novelty_coef": 0.03687120634474641
            },
            {
              "gen": 12,
              "best": -127.0,
              "mean": -180.53333333333333,
              "num_species": 6,
              "avg_complexity": 6.466666666666667,
              "max_complexity": 9,
              "archive_size": 5,
              "avg_mut_rate": 1.0744408825908445,
              "eff_novelty_coef": 0.03576507015440401
            },
            {
              "gen": 13,
              "best": -98.0,
              "mean": -172.81666666666666,
              "num_species": 8,
              "avg_complexity": 6.116666666666666,
              "max_complexity": 9,
              "archive_size": 5,
              "avg_mut_rate": 1.1953509658349233,
              "eff_novelty_coef": 0.03469211804977189
            },
            {
              "gen": 14,
              "best": -114.0,
              "mean": -168.15,
              "num_species": 9,
              "avg_complexity": 6.416666666666667,
              "max_complexity": 10,
              "archive_size": 5,
              "avg_mut_rate": 1.2792189438503418,
              "eff_novelty_coef": 0.03365135450827873
            },
            {
              "gen": 15,
              "best": -112.0,
              "mean": -167.81666666666666,
              "num_species": 10,
              "avg_complexity": 6.833333333333333,
              "max_complexity": 12,
              "archive_size": 5,
              "avg_mut_rate": 1.346666666666667,
              "eff_novelty_coef": 0.03264181387303037
            },
            {
              "gen": 16,
              "best": -121.0,
              "mean": -171.61666666666667,
              "num_species": 8,
              "avg_complexity": 6.666666666666667,
              "max_complexity": 10,
              "archive_size": 5,
              "avg_mut_rate": 1.3930555555555557,
              "eff_novelty_coef": 0.031662559456839455
            },
            {
              "gen": 17,
              "best": -122.0,
              "mean": -175.05,
              "num_species": 11,
              "avg_complexity": 7.266666666666667,
              "max_complexity": 10,
              "archive_size": 5,
              "avg_mut_rate": 1.390509259259259,
              "eff_novelty_coef": 0.030712682673134276
            },
            {
              "gen": 18,
              "best": -122.0,
              "mean": -172.6,
              "num_species": 5,
              "avg_complexity": 6.8,
              "max_complexity": 11,
              "archive_size": 5,
              "avg_mut_rate": 1.4541666666666666,
              "eff_novelty_coef": 0.029791302192940246
            },
            {
              "gen": 19,
              "best": -116.0,
              "mean": -163.8,
              "num_species": 6,
              "avg_complexity": 6.383333333333334,
              "max_complexity": 9,
              "archive_size": 5,
              "avg_mut_rate": 1.3895833333333336,
              "eff_novelty_coef": 0.02889756312715204
            },
            {
              "gen": 20,
              "best": -121.0,
              "mean": -171.68333333333334,
              "num_species": 5,
              "avg_complexity": 6.483333333333333,
              "max_complexity": 11,
              "archive_size": 5,
              "avg_mut_rate": 1.4789351851851853,
              "eff_novelty_coef": 0.028030636233337475
            },
            {
              "gen": 21,
              "best": -114.0,
              "mean": -162.46666666666667,
              "num_species": 5,
              "avg_complexity": 6.233333333333333,
              "max_complexity": 8,
              "archive_size": 5,
              "avg_mut_rate": 1.3375,
              "eff_novelty_coef": 0.02718971714633735
            },
            {
              "gen": 22,
              "best": -122.0,
              "mean": -165.71666666666667,
              "num_species": 8,
              "avg_complexity": 6.1,
              "max_complexity": 8,
              "archive_size": 5,
              "avg_mut_rate": 1.43125,
              "eff_novelty_coef": 0.02637402563194723
            },
            {
              "gen": 23,
              "best": -122.0,
              "mean": -177.65,
              "num_species": 6,
              "avg_complexity": 6.15,
              "max_complexity": 9,
              "archive_size": 5,
              "avg_mut_rate": 1.3420138888888888,
              "eff_novelty_coef": 0.025582804862988813
            },
            {
              "gen": 24,
              "best": -94.0,
              "mean": -158.88333333333333,
              "num_species": 5,
              "avg_complexity": 6.25,
              "max_complexity": 11,
              "archive_size": 5,
              "avg_mut_rate": 1.357445987654321,
              "eff_novelty_coef": 0.024815320717099146
            },
            {
              "gen": 25,
              "best": -122.0,
              "mean": -165.46666666666667,
              "num_species": 7,
              "avg_complexity": 6.066666666666666,
              "max_complexity": 8,
              "archive_size": 5,
              "avg_mut_rate": 1.4465277777777779,
              "eff_novelty_coef": 0.02407086109558617
            },
            {
              "gen": 26,
              "best": -95.0,
              "mean": -153.3,
              "num_species": 9,
              "avg_complexity": 6.2,
              "max_complexity": 8,
              "archive_size": 5,
              "avg_mut_rate": 1.4289351851851853,
              "eff_novelty_coef": 0.023348735262718585
            },
            {
              "gen": 27,
              "best": -93.0,
              "mean": -146.2,
              "num_species": 7,
              "avg_complexity": 6.433333333333334,
              "max_complexity": 10,
              "archive_size": 5,
              "avg_mut_rate": 1.5,
              "eff_novelty_coef": 0.022648273204837026
            },
            {
              "gen": 28,
              "best": -89.0,
              "mean": -157.75,
              "num_species": 5,
              "avg_complexity": 6.316666666666666,
              "max_complexity": 9,
              "archive_size": 5,
              "avg_mut_rate": 1.5,
              "eff_novelty_coef": 0.021968825008691916
            },
            {
              "gen": 29,
              "best": -114.0,
              "mean": -160.68333333333334,
              "num_species": 7,
              "avg_complexity": 6.35,
              "max_complexity": 10,
              "archive_size": 5,
              "avg_mut_rate": 1.4833333333333334,
              "eff_novelty_coef": 0.02130976025843116
            },
            {
              "gen": 30,
              "best": -114.0,
              "mean": -164.08333333333334,
              "num_species": 5,
              "avg_complexity": 6.2,
              "max_complexity": 9,
              "archive_size": 5,
              "avg_mut_rate": 1.5,
              "eff_novelty_coef": 0.020670467450678222
            },
            {
              "gen": 31,
              "best": -117.0,
              "mean": -166.66666666666666,
              "num_species": 4,
              "avg_complexity": 6.616666666666666,
              "max_complexity": 10,
              "archive_size": 5,
              "avg_mut_rate": 1.4708333333333334,
              "eff_novelty_coef": 0.020050353427157875
            },
            {
              "gen": 32,
              "best": -123.0,
              "mean": -177.78333333333333,
              "num_species": 6,
              "avg_complexity": 6.883333333333334,
              "max_complexity": 11,
              "archive_size": 5,
              "avg_mut_rate": 1.38125,
              "eff_novelty_coef": 0.01944884282434314
            },
            {
              "gen": 33,
              "best": -117.0,
              "mean": -179.26666666666668,
              "num_species": 5,
              "avg_complexity": 6.416666666666667,
              "max_complexity": 11,
              "archive_size": 5,
              "avg_mut_rate": 1.309027777777778,
              "eff_novelty_coef": 0.018865377539612843
            },
            {
              "gen": 34,
              "best": -124.0,
              "mean": -181.31666666666666,
              "num_species": 5,
              "avg_complexity": 6.166666666666667,
              "max_complexity": 8,
              "archive_size": 5,
              "avg_mut_rate": 1.2368055555555557,
              "eff_novelty_coef": 0.018299416213424458
            },
            {
              "gen": 35,
              "best": -95.0,
              "mean": -163.46666666666667,
              "num_species": 8,
              "avg_complexity": 6.066666666666666,
              "max_complexity": 8,
              "archive_size": 5,
              "avg_mut_rate": 1.231365740740741,
              "eff_novelty_coef": 0.017750433727021724
            },
            {
              "gen": 36,
              "best": -91.0,
              "mean": -155.58333333333334,
              "num_species": 11,
              "avg_complexity": 6.133333333333334,
              "max_complexity": 8,
              "archive_size": 5,
              "avg_mut_rate": 1.4497685185185185,
              "eff_novelty_coef": 0.017217920715211072
            },
            {
              "gen": 37,
              "best": -113.0,
              "mean": -156.03333333333333,
              "num_species": 14,
              "avg_complexity": 6.166666666666667,
              "max_complexity": 8,
              "archive_size": 5,
              "avg_mut_rate": 1.5,
              "eff_novelty_coef": 0.016701383093754737
            },
            {
              "gen": 38,
              "best": -113.0,
              "mean": -156.46666666666667,
              "num_species": 5,
              "avg_complexity": 6.5,
              "max_complexity": 8,
              "archive_size": 5,
              "avg_mut_rate": 1.4333333333333333,
              "eff_novelty_coef": 0.016200341600942095
            },
            {
              "gen": 39,
              "best": -122.0,
              "mean": -178.18333333333334,
              "num_species": 9,
              "avg_complexity": 7.15,
              "max_complexity": 10,
              "archive_size": 5,
              "avg_mut_rate": 1.4847222222222223,
              "eff_novelty_coef": 0.01571433135291383
            },
            {
              "gen": 40,
              "best": -123.0,
              "mean": -166.76666666666668,
              "num_species": 7,
              "avg_complexity": 6.666666666666667,
              "max_complexity": 11,
              "archive_size": 5,
              "avg_mut_rate": 1.4791666666666667,
              "eff_novelty_coef": 0.015242901412326416
            },
            {
              "gen": 41,
              "best": -90.0,
              "mean": -166.11666666666667,
              "num_species": 9,
              "avg_complexity": 6.783333333333333,
              "max_complexity": 11,
              "archive_size": 5,
              "avg_mut_rate": 1.3125,
              "eff_novelty_coef": 0.014785614369956623
            },
            {
              "gen": 42,
              "best": -119.0,
              "mean": -164.48333333333332,
              "num_species": 5,
              "avg_complexity": 6.35,
              "max_complexity": 10,
              "archive_size": 5,
              "avg_mut_rate": 1.1597222222222223,
              "eff_novelty_coef": 0.014342045938857927
            },
            {
              "gen": 43,
              "best": -113.0,
              "mean": -172.93333333333334,
              "num_species": 9,
              "avg_complexity": 6.55,
              "max_complexity": 10,
              "archive_size": 5,
              "avg_mut_rate": 1.0439814814814814,
              "eff_novelty_coef": 0.013911784560692187
            },
            {
              "gen": 44,
              "best": -113.0,
              "mean": -163.11666666666667,
              "num_species": 5,
              "avg_complexity": 6.633333333333334,
              "max_complexity": 10,
              "archive_size": 5,
              "avg_mut_rate": 1.1557870370370371,
              "eff_novelty_coef": 0.01349443102387142
            },
            {
              "gen": 45,
              "best": -90.0,
              "mean": -154.23333333333332,
              "num_species": 5,
              "avg_complexity": 6.333333333333333,
              "max_complexity": 9,
              "archive_size": 5,
              "avg_mut_rate": 1.2695601851851854,
              "eff_novelty_coef": 0.013089598093155278
            },
            {
              "gen": 46,
              "best": -95.0,
              "mean": -159.56666666666666,
              "num_species": 6,
              "avg_complexity": 6.15,
              "max_complexity": 9,
              "archive_size": 5,
              "avg_mut_rate": 1.0049768518518518,
              "eff_novelty_coef": 0.012696910150360619
            },
            {
              "gen": 47,
              "best": -120.0,
              "mean": -168.86666666666667,
              "num_species": 5,
              "avg_complexity": 6.033333333333333,
              "max_complexity": 8,
              "archive_size": 5,
              "avg_mut_rate": 1.087712191358025,
              "eff_novelty_coef": 0.0123160028458498
            },
            {
              "gen": 48,
              "best": -113.0,
              "mean": -162.98333333333332,
              "num_species": 5,
              "avg_complexity": 6.166666666666667,
              "max_complexity": 8,
              "archive_size": 5,
              "avg_mut_rate": 1.3541666666666667,
              "eff_novelty_coef": 0.011946522760474306
            },
            {
              "gen": 49,
              "best": -117.0,
              "mean": -174.56666666666666,
              "num_species": 8,
              "avg_complexity": 6.35,
              "max_complexity": 11,
              "archive_size": 5,
              "avg_mut_rate": 1.5,
              "eff_novelty_coef": 0.011588127077660076
            },
            {
              "gen": 50,
              "best": -114.0,
              "mean": -169.1,
              "num_species": 5,
              "avg_complexity": 6.583333333333333,
              "max_complexity": 11,
              "archive_size": 5,
              "avg_mut_rate": 1.5,
              "eff_novelty_coef": 0.011240483265330274
            },
            {
              "gen": 51,
              "best": -122.0,
              "mean": -162.85,
              "num_species": 5,
              "avg_complexity": 6.366666666666666,
              "max_complexity": 8,
              "archive_size": 5,
              "avg_mut_rate": 1.4541666666666666,
              "eff_novelty_coef": 0.010903268767370366
            },
            {
              "gen": 52,
              "best": -116.0,
              "mean": -164.58333333333334,
              "num_species": 9,
              "avg_complexity": 6.916666666666667,
              "max_complexity": 10,
              "archive_size": 5,
              "avg_mut_rate": 1.4500000000000002,
              "eff_novelty_coef": 0.010576170704349255
            },
            {
              "gen": 53,
              "best": -128.0,
              "mean": -172.61666666666667,
              "num_species": 4,
              "avg_complexity": 7.566666666666666,
              "max_complexity": 11,
              "archive_size": 5,
              "avg_mut_rate": 1.4708333333333334,
              "eff_novelty_coef": 0.010258885583218776
            },
            {
              "gen": 54,
              "best": -117.0,
              "mean": -164.23333333333332,
              "num_species": 7,
              "avg_complexity": 8.116666666666667,
              "max_complexity": 12,
              "archive_size": 5,
              "avg_mut_rate": 1.4541666666666666,
              "eff_novelty_coef": 0.009951119015722213
            },
            {
              "gen": 55,
              "best": -117.0,
              "mean": -167.68333333333334,
              "num_species": 3,
              "avg_complexity": 8.233333333333333,
              "max_complexity": 13,
              "archive_size": 5,
              "avg_mut_rate": 1.5,
              "eff_novelty_coef": 0.009652585445250546
            },
            {
              "gen": 56,
              "best": -118.0,
              "mean": -166.15,
              "num_species": 12,
              "avg_complexity": 9.033333333333333,
              "max_complexity": 12,
              "archive_size": 5,
              "avg_mut_rate": 1.4958333333333333,
              "eff_novelty_coef": 0.009363007881893029
            },
            {
              "gen": 57,
              "best": -117.0,
              "mean": -155.85,
              "num_species": 5,
              "avg_complexity": 9.416666666666666,
              "max_complexity": 13,
              "archive_size": 5,
              "avg_mut_rate": 1.425,
              "eff_novelty_coef": 0.009082117645436238
            },
            {
              "gen": 58,
              "best": -119.0,
              "mean": -172.03333333333333,
              "num_species": 11,
              "avg_complexity": 10.133333333333333,
              "max_complexity": 15,
              "archive_size": 5,
              "avg_mut_rate": 1.4180555555555554,
              "eff_novelty_coef": 0.00880965411607315
            },
            {
              "gen": 59,
              "best": -115.0,
              "mean": -157.16666666666666,
              "num_species": 5,
              "avg_complexity": 10.683333333333334,
              "max_complexity": 14,
              "archive_size": 5,
              "avg_mut_rate": 1.4368055555555557,
              "eff_novelty_coef": 0.008545364492590956
            },
            {
              "gen": 60,
              "best": -168.0,
              "mean": -192.85,
              "num_species": 5,
              "avg_complexity": 10.3,
              "max_complexity": 15,
              "archive_size": 5,
              "avg_mut_rate": 1.45,
              "eff_novelty_coef": 0.008289003557813228
            }
          ],
          "elapsed_s": 32.1646831035614,
          "final_best_fitness": -162.8,
          "final_best_std": 28.652399550473955,
          "final_best_min": -189.0,
          "final_best_max": -116.0,
          "final_best_evals": [
            -184.0,
            -177.0,
            -179.0,
            -178.0,
            -173.0,
            -135.0,
            -117.0,
            -174.0,
            -183.0,
            -184.0,
            -117.0,
            -184.0,
            -116.0,
            -189.0,
            -117.0,
            -184.0,
            -117.0,
            -181.0,
            -189.0,
            -178.0
          ],
          "final_best_complexity": 8,
          "final_best_hidden": 1,
          "first_solve_gen": null
        },
        {
          "seed": 2,
          "history": [
            {
              "gen": 1,
              "best": -200.0,
              "mean": -200.0,
              "num_species": 3,
              "avg_complexity": 6.0,
              "max_complexity": 6,
              "archive_size": 3,
              "avg_mut_rate": 0.4655555555555556,
              "eff_novelty_coef": 0.05
            },
            {
              "gen": 2,
              "best": -200.0,
              "mean": -200.0,
              "num_species": 5,
              "avg_complexity": 6.066666666666666,
              "max_complexity": 8,
              "archive_size": 8,
              "avg_mut_rate": 0.42269444444444454,
              "eff_novelty_coef": 0.0485
            },
            {
              "gen": 3,
              "best": -200.0,
              "mean": -200.0,
              "num_species": 6,
              "avg_complexity": 6.1,
              "max_complexity": 8,
              "archive_size": 8,
              "avg_mut_rate": 0.38707530864197537,
              "eff_novelty_coef": 0.047045000000000003
            },
            {
              "gen": 4,
              "best": -179.0,
              "mean": -198.6,
              "num_species": 6,
              "avg_complexity": 6.116666666666666,
              "max_complexity": 9,
              "archive_size": 8,
              "avg_mut_rate": 0.3429218106995885,
              "eff_novelty_coef": 0.04563365
            },
            {
              "gen": 5,
              "best": -200.0,
              "mean": -200.0,
              "num_species": 6,
              "avg_complexity": 6.033333333333333,
              "max_complexity": 8,
              "archive_size": 8,
              "avg_mut_rate": 0.29389274691358025,
              "eff_novelty_coef": 0.0442646405
            },
            {
              "gen": 6,
              "best": -200.0,
              "mean": -200.0,
              "num_species": 6,
              "avg_complexity": 6.1,
              "max_complexity": 8,
              "archive_size": 8,
              "avg_mut_rate": 0.22393511374028355,
              "eff_novelty_coef": 0.042936701285
            },
            {
              "gen": 7,
              "best": -200.0,
              "mean": -200.0,
              "num_species": 4,
              "avg_complexity": 6.033333333333333,
              "max_complexity": 8,
              "archive_size": 8,
              "avg_mut_rate": 0.19377569039590004,
              "eff_novelty_coef": 0.04164860024644999
            },
            {
              "gen": 8,
              "best": -200.0,
              "mean": -200.0,
              "num_species": 5,
              "avg_complexity": 6.133333333333334,
              "max_complexity": 8,
              "archive_size": 8,
              "avg_mut_rate": 0.16403799042955855,
              "eff_novelty_coef": 0.040399142239056496
            },
            {
              "gen": 9,
              "best": -200.0,
              "mean": -200.0,
              "num_species": 8,
              "avg_complexity": 6.5,
              "max_complexity": 10,
              "archive_size": 8,
              "avg_mut_rate": 0.1381195744873961,
              "eff_novelty_coef": 0.0391871679718848
            },
            {
              "gen": 10,
              "best": -200.0,
              "mean": -200.0,
              "num_species": 8,
              "avg_complexity": 6.7,
              "max_complexity": 10,
              "archive_size": 8,
              "avg_mut_rate": 0.11628401968068897,
              "eff_novelty_coef": 0.03801155293272826
            },
            {
              "gen": 11,
              "best": -200.0,
              "mean": -200.0,
              "num_species": 4,
              "avg_complexity": 6.0,
              "max_complexity": 6,
              "archive_size": 8,
              "avg_mut_rate": 0.09690334973390749,
              "eff_novelty_coef": 0.03687120634474641
            },
            {
              "gen": 12,
              "best": -200.0,
              "mean": -200.0,
              "num_species": 4,
              "avg_complexity": 6.0,
              "max_complexity": 6,
              "archive_size": 8,
              "avg_mut_rate": 0.08075279144492291,
              "eff_novelty_coef": 0.03576507015440401
            },
            {
              "gen": 13,
              "best": -200.0,
              "mean": -200.0,
              "num_species": 6,
              "avg_complexity": 6.0,
              "max_complexity": 6,
              "archive_size": 8,
              "avg_mut_rate": 0.06729399287076908,
              "eff_novelty_coef": 0.03469211804977189
            },
            {
              "gen": 14,
              "best": -200.0,
              "mean": -200.0,
              "num_species": 6,
              "avg_complexity": 6.0,
              "max_complexity": 6,
              "archive_size": 8,
              "avg_mut_rate": 0.05607832739230758,
              "eff_novelty_coef": 0.03365135450827873
            },
            {
              "gen": 15,
              "best": -200.0,
              "mean": -200.0,
              "num_species": 5,
              "avg_complexity": 6.0,
              "max_complexity": 6,
              "archive_size": 8,
              "avg_mut_rate": 0.04999999999999998,
              "eff_novelty_coef": 0.03264181387303037
            },
            {
              "gen": 16,
              "best": -200.0,
              "mean": -200.0,
              "num_species": 5,
              "avg_complexity": 6.0,
              "max_complexity": 6,
              "archive_size": 8,
              "avg_mut_rate": 0.04999999999999998,
              "eff_novelty_coef": 0.031662559456839455
            },
            {
              "gen": 17,
              "best": -200.0,
              "mean": -200.0,
              "num_species": 5,
              "avg_complexity": 6.0,
              "max_complexity": 6,
              "archive_size": 8,
              "avg_mut_rate": 0.04999999999999998,
              "eff_novelty_coef": 0.030712682673134276
            },
            {
              "gen": 18,
              "best": -200.0,
              "mean": -200.0,
              "num_species": 5,
              "avg_complexity": 6.0,
              "max_complexity": 6,
              "archive_size": 8,
              "avg_mut_rate": 0.04999999999999998,
              "eff_novelty_coef": 0.029791302192940246
            },
            {
              "gen": 19,
              "best": -200.0,
              "mean": -200.0,
              "num_species": 5,
              "avg_complexity": 6.0,
              "max_complexity": 6,
              "archive_size": 8,
              "avg_mut_rate": 0.04999999999999998,
              "eff_novelty_coef": 0.02889756312715204
            },
            {
              "gen": 20,
              "best": -200.0,
              "mean": -200.0,
              "num_species": 6,
              "avg_complexity": 6.0,
              "max_complexity": 6,
              "archive_size": 8,
              "avg_mut_rate": 0.04999999999999998,
              "eff_novelty_coef": 0.028030636233337475
            },
            {
              "gen": 21,
              "best": -200.0,
              "mean": -200.0,
              "num_species": 5,
              "avg_complexity": 6.0,
              "max_complexity": 6,
              "archive_size": 8,
              "avg_mut_rate": 0.04999999999999998,
              "eff_novelty_coef": 0.02718971714633735
            },
            {
              "gen": 22,
              "best": -200.0,
              "mean": -200.0,
              "num_species": 4,
              "avg_complexity": 6.0,
              "max_complexity": 6,
              "archive_size": 8,
              "avg_mut_rate": 0.04999999999999998,
              "eff_novelty_coef": 0.02637402563194723
            },
            {
              "gen": 23,
              "best": -200.0,
              "mean": -200.0,
              "num_species": 5,
              "avg_complexity": 6.0,
              "max_complexity": 6,
              "archive_size": 8,
              "avg_mut_rate": 0.04999999999999998,
              "eff_novelty_coef": 0.025582804862988813
            },
            {
              "gen": 24,
              "best": -200.0,
              "mean": -200.0,
              "num_species": 8,
              "avg_complexity": 6.0,
              "max_complexity": 6,
              "archive_size": 8,
              "avg_mut_rate": 0.04999999999999998,
              "eff_novelty_coef": 0.024815320717099146
            },
            {
              "gen": 25,
              "best": -200.0,
              "mean": -200.0,
              "num_species": 4,
              "avg_complexity": 6.0,
              "max_complexity": 6,
              "archive_size": 8,
              "avg_mut_rate": 0.04999999999999998,
              "eff_novelty_coef": 0.02407086109558617
            },
            {
              "gen": 26,
              "best": -200.0,
              "mean": -200.0,
              "num_species": 6,
              "avg_complexity": 6.0,
              "max_complexity": 6,
              "archive_size": 8,
              "avg_mut_rate": 0.04999999999999998,
              "eff_novelty_coef": 0.023348735262718585
            },
            {
              "gen": 27,
              "best": -200.0,
              "mean": -200.0,
              "num_species": 5,
              "avg_complexity": 6.033333333333333,
              "max_complexity": 8,
              "archive_size": 8,
              "avg_mut_rate": 0.04999999999999998,
              "eff_novelty_coef": 0.022648273204837026
            },
            {
              "gen": 28,
              "best": -200.0,
              "mean": -200.0,
              "num_species": 4,
              "avg_complexity": 6.0,
              "max_complexity": 6,
              "archive_size": 8,
              "avg_mut_rate": 0.04999999999999998,
              "eff_novelty_coef": 0.021968825008691916
            },
            {
              "gen": 29,
              "best": -200.0,
              "mean": -200.0,
              "num_species": 5,
              "avg_complexity": 6.0,
              "max_complexity": 6,
              "archive_size": 8,
              "avg_mut_rate": 0.04999999999999998,
              "eff_novelty_coef": 0.02130976025843116
            },
            {
              "gen": 30,
              "best": -200.0,
              "mean": -200.0,
              "num_species": 5,
              "avg_complexity": 6.0,
              "max_complexity": 6,
              "archive_size": 8,
              "avg_mut_rate": 0.04999999999999998,
              "eff_novelty_coef": 0.020670467450678222
            },
            {
              "gen": 31,
              "best": -200.0,
              "mean": -200.0,
              "num_species": 6,
              "avg_complexity": 6.0,
              "max_complexity": 6,
              "archive_size": 8,
              "avg_mut_rate": 0.04999999999999998,
              "eff_novelty_coef": 0.020050353427157875
            },
            {
              "gen": 32,
              "best": -200.0,
              "mean": -200.0,
              "num_species": 5,
              "avg_complexity": 6.0,
              "max_complexity": 6,
              "archive_size": 8,
              "avg_mut_rate": 0.04999999999999998,
              "eff_novelty_coef": 0.01944884282434314
            },
            {
              "gen": 33,
              "best": -200.0,
              "mean": -200.0,
              "num_species": 4,
              "avg_complexity": 6.033333333333333,
              "max_complexity": 8,
              "archive_size": 8,
              "avg_mut_rate": 0.04999999999999998,
              "eff_novelty_coef": 0.018865377539612843
            },
            {
              "gen": 34,
              "best": -200.0,
              "mean": -200.0,
              "num_species": 4,
              "avg_complexity": 6.1,
              "max_complexity": 8,
              "archive_size": 8,
              "avg_mut_rate": 0.04999999999999998,
              "eff_novelty_coef": 0.018299416213424458
            },
            {
              "gen": 35,
              "best": -125.0,
              "mean": -181.25,
              "num_species": 4,
              "avg_complexity": 6.033333333333333,
              "max_complexity": 8,
              "archive_size": 8,
              "avg_mut_rate": 0.04999999999999998,
              "eff_novelty_coef": 0.017750433727021724
            },
            {
              "gen": 36,
              "best": -133.0,
              "mean": -164.26666666666668,
              "num_species": 2,
              "avg_complexity": 6.0,
              "max_complexity": 6,
              "archive_size": 8,
              "avg_mut_rate": 0.04999999999999998,
              "eff_novelty_coef": 0.017217920715211072
            },
            {
              "gen": 37,
              "best": -119.0,
              "mean": -175.95,
              "num_species": 4,
              "avg_complexity": 6.0,
              "max_complexity": 6,
              "archive_size": 8,
              "avg_mut_rate": 0.05299999999999998,
              "eff_novelty_coef": 0.016701383093754737
            },
            {
              "gen": 38,
              "best": -126.0,
              "mean": -180.08333333333334,
              "num_species": 7,
              "avg_complexity": 6.0,
              "max_complexity": 6,
              "archive_size": 8,
              "avg_mut_rate": 0.05806666666666664,
              "eff_novelty_coef": 0.016200341600942095
            },
            {
              "gen": 39,
              "best": -164.0,
              "mean": -191.0,
              "num_species": 5,
              "avg_complexity": 6.0,
              "max_complexity": 6,
              "archive_size": 8,
              "avg_mut_rate": 0.05909999999999998,
              "eff_novelty_coef": 0.01571433135291383
            },
            {
              "gen": 40,
              "best": -130.0,
              "mean": -185.93333333333334,
              "num_species": 4,
              "avg_complexity": 6.0,
              "max_complexity": 6,
              "archive_size": 8,
              "avg_mut_rate": 0.06525333333333332,
              "eff_novelty_coef": 0.015242901412326416
            },
            {
              "gen": 41,
              "best": -126.0,
              "mean": -180.8,
              "num_species": 4,
              "avg_complexity": 6.0,
              "max_complexity": 6,
              "archive_size": 8,
              "avg_mut_rate": 0.07680533333333332,
              "eff_novelty_coef": 0.014785614369956623
            },
            {
              "gen": 42,
              "best": -119.0,
              "mean": -158.91666666666666,
              "num_species": 5,
              "avg_complexity": 6.0,
              "max_complexity": 6,
              "archive_size": 8,
              "avg_mut_rate": 0.09906704,
              "eff_novelty_coef": 0.014342045938857927
            },
            {
              "gen": 43,
              "best": -162.0,
              "mean": -189.23333333333332,
              "num_species": 4,
              "avg_complexity": 6.033333333333333,
              "max_complexity": 8,
              "archive_size": 8,
              "avg_mut_rate": 0.13277951999999998,
              "eff_novelty_coef": 0.013911784560692187
            },
            {
              "gen": 44,
              "best": -130.0,
              "mean": -181.7,
              "num_species": 4,
              "avg_complexity": 6.1,
              "max_complexity": 8,
              "archive_size": 8,
              "avg_mut_rate": 0.14159715839999992,
              "eff_novelty_coef": 0.01349443102387142
            },
            {
              "gen": 45,
              "best": -145.0,
              "mean": -175.58333333333334,
              "num_species": 5,
              "avg_complexity": 6.0,
              "max_complexity": 6,
              "archive_size": 8,
              "avg_mut_rate": 0.15072915456,
              "eff_novelty_coef": 0.013089598093155278
            },
            {
              "gen": 46,
              "best": -116.0,
              "mean": -174.8,
              "num_species": 4,
              "avg_complexity": 6.0,
              "max_complexity": 6,
              "archive_size": 8,
              "avg_mut_rate": 0.14774814720000004,
              "eff_novelty_coef": 0.012696910150360619
            },
            {
              "gen": 47,
              "best": -125.0,
              "mean": -176.95,
              "num_species": 4,
              "avg_complexity": 6.0,
              "max_complexity": 6,
              "archive_size": 8,
              "avg_mut_rate": 0.13820313599999995,
              "eff_novelty_coef": 0.0123160028458498
            },
            {
              "gen": 48,
              "best": -126.0,
              "mean": -180.0,
              "num_species": 7,
              "avg_complexity": 6.033333333333333,
              "max_complexity": 8,
              "archive_size": 8,
              "avg_mut_rate": 0.1840094975999999,
              "eff_novelty_coef": 0.011946522760474306
            },
            {
              "gen": 49,
              "best": -120.0,
              "mean": -166.95,
              "num_species": 4,
              "avg_complexity": 6.333333333333333,
              "max_complexity": 8,
              "archive_size": 8,
              "avg_mut_rate": 0.20335830783999995,
              "eff_novelty_coef": 0.011588127077660076
            },
            {
              "gen": 50,
              "best": -124.0,
              "mean": -173.96666666666667,
              "num_species": 5,
              "avg_complexity": 6.433333333333334,
              "max_complexity": 8,
              "archive_size": 8,
              "avg_mut_rate": 0.25157061478399995,
              "eff_novelty_coef": 0.011240483265330274
            },
            {
              "gen": 51,
              "best": -133.0,
              "mean": -173.46666666666667,
              "num_species": 4,
              "avg_complexity": 6.233333333333333,
              "max_complexity": 8,
              "archive_size": 8,
              "avg_mut_rate": 0.19832716202666661,
              "eff_novelty_coef": 0.010903268767370366
            },
            {
              "gen": 52,
              "best": -116.0,
              "mean": -156.0,
              "num_species": 4,
              "avg_complexity": 6.216666666666667,
              "max_complexity": 9,
              "archive_size": 8,
              "avg_mut_rate": 0.23519371153066662,
              "eff_novelty_coef": 0.010576170704349255
            },
            {
              "gen": 53,
              "best": -149.0,
              "mean": -193.2,
              "num_species": 4,
              "avg_complexity": 6.533333333333333,
              "max_complexity": 9,
              "archive_size": 8,
              "avg_mut_rate": 0.26122326545066665,
              "eff_novelty_coef": 0.010258885583218776
            },
            {
              "gen": 54,
              "best": -122.0,
              "mean": -180.5,
              "num_species": 5,
              "avg_complexity": 6.55,
              "max_complexity": 9,
              "archive_size": 8,
              "avg_mut_rate": 0.31335624231253323,
              "eff_novelty_coef": 0.009951119015722213
            },
            {
              "gen": 55,
              "best": -115.0,
              "mean": -164.88333333333333,
              "num_species": 6,
              "avg_complexity": 6.033333333333333,
              "max_complexity": 8,
              "archive_size": 8,
              "avg_mut_rate": 0.38951038691054923,
              "eff_novelty_coef": 0.009652585445250546
            },
            {
              "gen": 56,
              "best": -118.0,
              "mean": -168.68333333333334,
              "num_species": 5,
              "avg_complexity": 6.116666666666666,
              "max_complexity": 9,
              "archive_size": 8,
              "avg_mut_rate": 0.5334333730241192,
              "eff_novelty_coef": 0.009363007881893029
            },
            {
              "gen": 57,
              "best": -134.0,
              "mean": -180.91666666666666,
              "num_species": 4,
              "avg_complexity": 6.066666666666666,
              "max_complexity": 8,
              "archive_size": 8,
              "avg_mut_rate": 0.6022691603591437,
              "eff_novelty_coef": 0.009082117645436238
            },
            {
              "gen": 58,
              "best": -124.0,
              "mean": -174.1,
              "num_species": 4,
              "avg_complexity": 6.15,
              "max_complexity": 9,
              "archive_size": 8,
              "avg_mut_rate": 0.720389659097639,
              "eff_novelty_coef": 0.00880965411607315
            },
            {
              "gen": 59,
              "best": -122.0,
              "mean": -175.2,
              "num_species": 5,
              "avg_complexity": 6.166666666666667,
              "max_complexity": 8,
              "archive_size": 8,
              "avg_mut_rate": 1.058462382174083,
              "eff_novelty_coef": 0.008545364492590956
            },
            {
              "gen": 60,
              "best": -114.0,
              "mean": -166.85,
              "num_species": 9,
              "avg_complexity": 6.233333333333333,
              "max_complexity": 10,
              "archive_size": 8,
              "avg_mut_rate": 1.2633757691160814,
              "eff_novelty_coef": 0.008289003557813228
            }
          ],
          "elapsed_s": 29.464248418807983,
          "final_best_fitness": -120.45,
          "final_best_std": 3.993432107849086,
          "final_best_min": -125.0,
          "final_best_max": -114.0,
          "final_best_evals": [
            -123.0,
            -122.0,
            -122.0,
            -122.0,
            -123.0,
            -116.0,
            -115.0,
            -123.0,
            -123.0,
            -123.0,
            -114.0,
            -124.0,
            -114.0,
            -125.0,
            -114.0,
            -124.0,
            -114.0,
            -122.0,
            -124.0,
            -122.0
          ],
          "final_best_complexity": 6,
          "final_best_hidden": 0,
          "first_solve_gen": null
        }
      ],
      "mean_final": -151.88333333333335,
      "std_final": 22.569608375473027,
      "mean_time": 33.1661585966746,
      "mean_complexity": 8.333333333333334,
      "solve_rate": 0.0
    }
  }
}